{"nodes": [{"id": "f_storage_platform_src_lib_file_summary_target_ts", "label": "target.ts", "file_type": "code", "source_file": "F:\\storage-platform\\src\\lib\\file-summary\\target.ts", "source_location": "L1"}, {"id": "target_getsummarytarget", "label": "getSummaryTarget()", "file_type": "code", "source_file": "F:\\storage-platform\\src\\lib\\file-summary\\target.ts", "source_location": "L7"}], "edges": [{"source": "f_storage_platform_src_lib_file_summary_target_ts", "target": "drizzle_orm", "relation": "imports_from", "confidence": "EXTRACTED", "source_file": "F:\\storage-platform\\src\\lib\\file-summary\\target.ts", "source_location": "L1", "weight": 1.0}, {"source": "f_storage_platform_src_lib_file_summary_target_ts", "target": "db", "relation": "imports_from", "confidence": "EXTRACTED", "source_file": "F:\\storage-platform\\src\\lib\\file-summary\\target.ts", "source_location": "L2", "weight": 1.0}, {"source": "f_storage_platform_src_lib_file_summary_target_ts", "target": "storage", "relation": "imports_from", "confidence": "EXTRACTED", "source_file": "F:\\storage-platform\\src\\lib\\file-summary\\target.ts", "source_location": "L3", "weight": 1.0}, {"source": "f_storage_platform_src_lib_file_summary_target_ts", "target": "storage_provider", "relation": "imports_from", "confidence": "EXTRACTED", "source_file": "F:\\storage-platform\\src\\lib\\file-summary\\target.ts", "source_location": "L4", "weight": 1.0}, {"source": "f_storage_platform_src_lib_file_summary_target_ts", "target": "f_storage_platform_src_lib_file_summary_types", "relation": "imports_from", "confidence": "EXTRACTED", "source_file": "F:\\storage-platform\\src\\lib\\file-summary\\target.ts", "source_location": "L5", "weight": 1.0}, {"source": "f_storage_platform_src_lib_file_summary_target_ts", "target": "target_getsummarytarget", "relation": "contains", "confidence": "EXTRACTED", "source_file": "F:\\storage-platform\\src\\lib\\file-summary\\target.ts", "source_location": "L7", "weight": 1.0}], "raw_calls": [{"caller_nid": "target_getsummarytarget", "callee": "limit", "source_file": "F:\\storage-platform\\src\\lib\\file-summary\\target.ts", "source_location": "L11"}, {"caller_nid": "target_getsummarytarget", "callee": "where", "source_file": "F:\\storage-platform\\src\\lib\\file-summary\\target.ts", "source_location": "L11"}, {"caller_nid": "target_getsummarytarget", "callee": "leftJoin", "source_file": "F:\\storage-platform\\src\\lib\\file-summary\\target.ts", "source_location": "L11"}, {"caller_nid": "target_getsummarytarget", "callee": "from", "source_file": "F:\\storage-platform\\src\\lib\\file-summary\\target.ts", "source_location": "L11"}, {"caller_nid": "target_getsummarytarget", "callee": "select", "source_file": "F:\\storage-platform\\src\\lib\\file-summary\\target.ts", "source_location": "L11"}, {"caller_nid": "target_getsummarytarget", "callee": "eq", "source_file": "F:\\storage-platform\\src\\lib\\file-summary\\target.ts", "source_location": "L26"}, {"caller_nid": "target_getsummarytarget", "callee": "and", "source_file": "F:\\storage-platform\\src\\lib\\file-summary\\target.ts", "source_location": "L28"}, {"caller_nid": "target_getsummarytarget", "callee": "eq", "source_file": "F:\\storage-platform\\src\\lib\\file-summary\\target.ts", "source_location": "L29"}, {"caller_nid": "target_getsummarytarget", "callee": "eq", "source_file": "F:\\storage-platform\\src\\lib\\file-summary\\target.ts", "source_location": "L30"}, {"caller_nid": "target_getsummarytarget", "callee": "eq", "source_file": "F:\\storage-platform\\src\\lib\\file-summary\\target.ts", "source_location": "L31"}]}