{"nodes": [{"id": "f_storage_platform_src_routes_app_trash_index_tsx", "label": "index.tsx", "file_type": "code", "source_file": "F:\\storage-platform\\src\\routes\\_app\\trash\\index.tsx", "source_location": "L1"}], "edges": [{"source": "f_storage_platform_src_routes_app_trash_index_tsx", "target": "react_router", "relation": "imports_from", "confidence": "EXTRACTED", "source_file": "F:\\storage-platform\\src\\routes\\_app\\trash\\index.tsx", "source_location": "L1", "weight": 1.0}, {"source": "f_storage_platform_src_routes_app_trash_index_tsx", "target": "react_start", "relation": "imports_from", "confidence": "EXTRACTED", "source_file": "F:\\storage-platform\\src\\routes\\_app\\trash\\index.tsx", "source_location": "L2", "weight": 1.0}, {"source": "f_storage_platform_src_routes_app_trash_index_tsx", "target": "react", "relation": "imports_from", "confidence": "EXTRACTED", "source_file": "F:\\storage-platform\\src\\routes\\_app\\trash\\index.tsx", "source_location": "L3", "weight": 1.0}, {"source": "f_storage_platform_src_routes_app_trash_index_tsx", "target": "page_skeleton", "relation": "imports_from", "confidence": "EXTRACTED", "source_file": "F:\\storage-platform\\src\\routes\\_app\\trash\\index.tsx", "source_location": "L4", "weight": 1.0}, {"source": "f_storage_platform_src_routes_app_trash_index_tsx", "target": "isauthenticated", "relation": "imports_from", "confidence": "EXTRACTED", "source_file": "F:\\storage-platform\\src\\routes\\_app\\trash\\index.tsx", "source_location": "L5", "weight": 1.0}], "raw_calls": []}