{"nodes": [{"id": "f_storage_platform_src_lib_s3_provider_client_factory_ts", "label": "s3-provider-client-factory.ts", "file_type": "code", "source_file": "F:\\storage-platform\\src\\lib\\s3-provider-client-factory.ts", "source_location": "L1"}, {"id": "s3_provider_client_factory_safetrim", "label": "safeTrim()", "file_type": "code", "source_file": "F:\\storage-platform\\src\\lib\\s3-provider-client-factory.ts", "source_location": "L28"}, {"id": "s3_provider_client_factory_resolveregion", "label": "resolveRegion()", "file_type": "code", "source_file": "F:\\storage-platform\\src\\lib\\s3-provider-client-factory.ts", "source_location": "L32"}, {"id": "s3_provider_client_factory_fromproviderrow", "label": "fromProviderRow()", "file_type": "code", "source_file": "F:\\storage-platform\\src\\lib\\s3-provider-client-factory.ts", "source_location": "L47"}], "edges": [{"source": "f_storage_platform_src_lib_s3_provider_client_factory_ts", "target": "client_s3", "relation": "imports_from", "confidence": "EXTRACTED", "source_file": "F:\\storage-platform\\src\\lib\\s3-provider-client-factory.ts", "source_location": "L1", "weight": 1.0}, {"source": "f_storage_platform_src_lib_s3_provider_client_factory_ts", "target": "storage_provider", "relation": "imports_from", "confidence": "EXTRACTED", "source_file": "F:\\storage-platform\\src\\lib\\s3-provider-client-factory.ts", "source_location": "L2", "weight": 1.0}, {"source": "f_storage_platform_src_lib_s3_provider_client_factory_ts", "target": "provider_crypto", "relation": "imports_from", "confidence": "EXTRACTED", "source_file": "F:\\storage-platform\\src\\lib\\s3-provider-client-factory.ts", "source_location": "L3", "weight": 1.0}, {"source": "f_storage_platform_src_lib_s3_provider_client_factory_ts", "target": "storage_provider_constants", "relation": "imports_from", "confidence": "EXTRACTED", "source_file": "F:\\storage-platform\\src\\lib\\s3-provider-client-factory.ts", "source_location": "L4", "weight": 1.0}, {"source": "f_storage_platform_src_lib_s3_provider_client_factory_ts", "target": "s3_provider_client_factory_safetrim", "relation": "contains", "confidence": "EXTRACTED", "source_file": "F:\\storage-platform\\src\\lib\\s3-provider-client-factory.ts", "source_location": "L28", "weight": 1.0}, {"source": "f_storage_platform_src_lib_s3_provider_client_factory_ts", "target": "s3_provider_client_factory_resolveregion", "relation": "contains", "confidence": "EXTRACTED", "source_file": "F:\\storage-platform\\src\\lib\\s3-provider-client-factory.ts", "source_location": "L32", "weight": 1.0}, {"source": "f_storage_platform_src_lib_s3_provider_client_factory_ts", "target": "s3_provider_client_factory_fromproviderrow", "relation": "contains", "confidence": "EXTRACTED", "source_file": "F:\\storage-platform\\src\\lib\\s3-provider-client-factory.ts", "source_location": "L47", "weight": 1.0}, {"source": "s3_provider_client_factory_resolveregion", "target": "s3_provider_client_factory_safetrim", "relation": "calls", "confidence": "EXTRACTED", "source_file": "F:\\storage-platform\\src\\lib\\s3-provider-client-factory.ts", "source_location": "L33", "weight": 1.0}, {"source": "s3_provider_client_factory_fromproviderrow", "target": "s3_provider_client_factory_safetrim", "relation": "calls", "confidence": "EXTRACTED", "source_file": "F:\\storage-platform\\src\\lib\\s3-provider-client-factory.ts", "source_location": "L48", "weight": 1.0}, {"source": "s3_provider_client_factory_fromproviderrow", "target": "s3_provider_client_factory_resolveregion", "relation": "calls", "confidence": "EXTRACTED", "source_file": "F:\\storage-platform\\src\\lib\\s3-provider-client-factory.ts", "source_location": "L52", "weight": 1.0}], "raw_calls": [{"caller_nid": "s3_provider_client_factory_safetrim", "callee": "trim", "source_file": "F:\\storage-platform\\src\\lib\\s3-provider-client-factory.ts", "source_location": "L29"}, {"caller_nid": "s3_provider_client_factory_safetrim", "callee": "replace", "source_file": "F:\\storage-platform\\src\\lib\\s3-provider-client-factory.ts", "source_location": "L29"}, {"caller_nid": "s3_provider_client_factory_resolveregion", "callee": "toLowerCase", "source_file": "F:\\storage-platform\\src\\lib\\s3-provider-client-factory.ts", "source_location": "L33"}, {"caller_nid": "s3_provider_client_factory_resolveregion", "callee": "has", "source_file": "F:\\storage-platform\\src\\lib\\s3-provider-client-factory.ts", "source_location": "L35"}, {"caller_nid": "s3_provider_client_factory_resolveregion", "callee": "warn", "source_file": "F:\\storage-platform\\src\\lib\\s3-provider-client-factory.ts", "source_location": "L41"}, {"caller_nid": "s3_provider_client_factory_fromproviderrow", "callee": "decryptProviderSecret", "source_file": "F:\\storage-platform\\src\\lib\\s3-provider-client-factory.ts", "source_location": "L48"}, {"caller_nid": "s3_provider_client_factory_fromproviderrow", "callee": "decryptProviderSecret", "source_file": "F:\\storage-platform\\src\\lib\\s3-provider-client-factory.ts", "source_location": "L50"}, {"caller_nid": "s3_provider_client_factory_fromproviderrow", "callee": "push", "source_file": "F:\\storage-platform\\src\\lib\\s3-provider-client-factory.ts", "source_location": "L57"}, {"caller_nid": "s3_provider_client_factory_fromproviderrow", "callee": "push", "source_file": "F:\\storage-platform\\src\\lib\\s3-provider-client-factory.ts", "source_location": "L58"}, {"caller_nid": "s3_provider_client_factory_fromproviderrow", "callee": "push", "source_file": "F:\\storage-platform\\src\\lib\\s3-provider-client-factory.ts", "source_location": "L59"}, {"caller_nid": "s3_provider_client_factory_fromproviderrow", "callee": "join", "source_file": "F:\\storage-platform\\src\\lib\\s3-provider-client-factory.ts", "source_location": "L61"}]}